akshare_one/__init__.py
akshare_one/eastmoney/client.py
akshare_one/eastmoney/utils.py
akshare_one/indicators.py
akshare_one/modules/cache.py
akshare_one/modules/financial/base.py
akshare_one/modules/financial/eastmoney_direct.py
akshare_one/modules/financial/factory.py
akshare_one/modules/financial/sina.py
akshare_one/modules/futures/__init__.py
akshare_one/modules/futures/base.py
akshare_one/modules/futures/factory.py
akshare_one/modules/futures/sina.py
akshare_one/modules/historical/base.py
akshare_one/modules/historical/eastmoney.py
akshare_one/modules/historical/eastmoney_direct.py
akshare_one/modules/historical/factory.py
akshare_one/modules/historical/sina.py
akshare_one/modules/indicators/__init__.py
akshare_one/modules/indicators/base.py
akshare_one/modules/indicators/factory.py
akshare_one/modules/indicators/simple.py
akshare_one/modules/indicators/talib.py
akshare_one/modules/info/base.py
akshare_one/modules/info/eastmoney.py
akshare_one/modules/info/factory.py
akshare_one/modules/insider/base.py
akshare_one/modules/insider/factory.py
akshare_one/modules/insider/xueqiu.py
akshare_one/modules/news/base.py
akshare_one/modules/news/eastmoney.py
akshare_one/modules/news/factory.py
akshare_one/modules/options/__init__.py
akshare_one/modules/options/base.py
akshare_one/modules/options/factory.py
akshare_one/modules/options/sina.py
akshare_one/modules/realtime/base.py
akshare_one/modules/realtime/eastmoney.py
akshare_one/modules/realtime/eastmoney_direct.py
akshare_one/modules/realtime/factory.py
akshare_one/modules/realtime/xueqiu.py
akshare_one/modules/utils.py
akshare_one/py.typed
akshare_one-0.3.17.dist-info/WHEEL
akshare_one-0.3.17.dist-info/METADATA
akshare_one-0.3.17.dist-info/RECORD
