Metadata-Version: 2.4
Name: akshare-one
Version: 0.3.17
Summary: Standardized interface for Chinese financial market data, built on AKShare with unified data formats and simplified APIs
Keywords: akshare,financial-data,stock-data,quant
License-Expression: MIT
Requires-Dist: akshare>=1.17.80
Requires-Dist: cachetools>=5.5.0
Requires-Dist: ta-lib>=0.6.4 ; extra == 'talib'
Requires-Python: >=3.10
Project-URL: Homepage, https://github.com/zwldarren/akshare-one
Project-URL: Repository, https://github.com/zwldarren/akshare-one.git
Provides-Extra: talib
